lite3/__init__.py
lite3-0.0.1.dist-info/LICENSE.txt
lite3-0.0.1.dist-info/METADATA
lite3-0.0.1.dist-info/WHEEL
lite3-0.0.1.dist-info/top_level.txt
lite3-0.0.1.dist-info/RECORD
