Metadata-Version: 2.1
Name: lite3
Version: 0.0.1
Summary: Maintain sqlite3 databases easily and without MYSQL syntax
Home-page: UNKNOWN
Author: Rogers Kabuye
Author-email: rogerskabuye0@gmail.com
License: UNKNOWN
Platform: UNKNOWN
Classifier: Development Status :: 5 - Production/Stable
Classifier: License :: OSI Approved :: MIT License
Classifier: Programming Language :: Python :: 3.6
Classifier: Programming Language :: Python :: 3.7
Classifier: Programming Language :: Python :: 3.8
Classifier: Programming Language :: Python :: 3.9
